pyexiv2/__init__.py
pyexiv2/convert.py
pyexiv2/core.py
pyexiv2/reference.py
pyexiv2/lib/README.md
pyexiv2/lib/__init__.py
pyexiv2/lib/exiv2api.cpp
pyexiv2/lib/libexiv2.dylib
pyexiv2/lib/py3.10-darwin/exiv2api.so
pyexiv2-2.15.2.dist-info/LICENSE
pyexiv2-2.15.2.dist-info/METADATA
pyexiv2-2.15.2.dist-info/WHEEL
pyexiv2-2.15.2.dist-info/top_level.txt
pyexiv2-2.15.2.dist-info/RECORD
