Metadata-Version: 2.1
Name: pyexiv2
Version: 2.15.2
Summary: Read and write image metadata, including EXIF, IPTC, XMP, ICC Profile.
Home-page: https://github.com/LeoHsiao1/pyexiv2
Author: LeoHsiao
Author-email: leohsiao@foxmail.com
License: GPLv3
Classifier: License :: OSI Approved :: GNU General Public License v3 (GPLv3)
Classifier: Operating System :: POSIX :: Linux
Classifier: Operating System :: MacOS
Classifier: Operating System :: Microsoft :: Windows
Requires-Python: >=3.6
License-File: LICENSE
